gwonir_interpreter/__init__.py
gwonir_interpreter/gwonir_core.py
gwonir_interpreter-0.1.0.dist-info/METADATA
gwonir_interpreter-0.1.0.dist-info/WHEEL
gwonir_interpreter-0.1.0.dist-info/entry_points.txt
gwonir_interpreter-0.1.0.dist-info/top_level.txt
gwonir_interpreter-0.1.0.dist-info/RECORD
