Metadata-Version: 2.1
Name: gwonir-interpreter
Version: 0.1.0
Summary: A simple interpreter for the Gwonir programming language.
Home-page: https://github.com/yourusername/gwonir_interpreter_project
Author: Your Name
Classifier: Programming Language :: Python :: 3
Classifier: License :: OSI Approved :: MIT License
Classifier: Operating System :: OS Independent
